AUTHORS.rst
CONTRIBUTING.rst
HISTORY.rst
LICENSE
MANIFEST.in
README.rst
setup.py
docs/Makefile
docs/conf.py
docs/index.rst
docs/api/flipper.rst
docs/dev/authors.rst
docs/dev/contributing.rst
docs/dev/philosophy.rst
docs/dev/todo.rst
docs/images/S_2_1.png
docs/images/ex1.png
docs/images/ex2.png
docs/templates/summary.rst
docs/user/citing.rst
docs/user/history.rst
docs/user/install.rst
docs/user/license.rst
docs/user/samples.rst
docs/user/taste.rst
docs/user/walkthrough.rst
flipper/__init__.py
flipper/__main__.py
flipper/app.py
flipper/census.py
flipper/load.py
flipper/surface.py
flipper.egg-info/PKG-INFO
flipper.egg-info/SOURCES.txt
flipper.egg-info/dependency_links.txt
flipper.egg-info/entry_points.txt
flipper.egg-info/not-zip-safe
flipper.egg-info/requires.txt
flipper.egg-info/top_level.txt
flipper/application/__init__.py
flipper/application/choicebox.py
flipper/application/inputbox.py
flipper/application/main.py
flipper/application/options.py
flipper/application/pieces.py
flipper/application/progress.py
flipper/application/spinning_icon.py
flipper/application/widgets.py
flipper/application/frames/tmp-0.gif
flipper/application/frames/tmp-1.gif
flipper/application/frames/tmp-10.gif
flipper/application/frames/tmp-11.gif
flipper/application/frames/tmp-2.gif
flipper/application/frames/tmp-3.gif
flipper/application/frames/tmp-4.gif
flipper/application/frames/tmp-5.gif
flipper/application/frames/tmp-6.gif
flipper/application/frames/tmp-7.gif
flipper/application/frames/tmp-8.gif
flipper/application/frames/tmp-9.gif
flipper/application/icon/icon.gif
flipper/application/icon/icon.ico
flipper/application/icon/icon.svg
flipper/application/icon/icon.tex
flipper/censuses/CHW.csv
flipper/censuses/hard.csv
flipper/censuses/knots.csv
flipper/kernel/__init__.py
flipper/kernel/bundle.py
flipper/kernel/decorators.py
flipper/kernel/encoding.py
flipper/kernel/equippedtriangulation.py
flipper/kernel/error.py
flipper/kernel/flatstructure.py
flipper/kernel/lamination.py
flipper/kernel/matrix.py
flipper/kernel/moves.py
flipper/kernel/permutation.py
flipper/kernel/splittingsequence.py
flipper/kernel/taut.py
flipper/kernel/triangulation.py
flipper/kernel/triangulation3.py
flipper/kernel/utilities.py
