Metadata-Version: 2.1
Name: flipper
Version: 0.15.5
Summary: For manipulating curves and measured laminations on surfaces and producing mapping tori.
Home-page: https://github.com/MarkCBell/flipper
Author: Mark Bell
Author-email: mcbell@illinois.edu
License: MIT License
Keywords: flipper
Classifier: Development Status :: 4 - Beta
Classifier: Intended Audience :: Education
Classifier: Intended Audience :: Science/Research
Classifier: License :: OSI Approved :: MIT License
Classifier: Natural Language :: English
Classifier: Operating System :: OS Independent
Classifier: Programming Language :: Python
Classifier: Topic :: Scientific/Engineering :: Mathematics
License-File: LICENSE
License-File: AUTHORS.rst
Requires-Dist: decorator>=4.3.0
Requires-Dist: numpy>=1.15.1
Requires-Dist: networkx>=2.0
Requires-Dist: pandas>=1.0.0
Requires-Dist: realalg>=0.3.2
